topsis_arihan_102303750/__init__.py
topsis_arihan_102303750/topsis.py
topsis_arihan_102303750-0.0.5.dist-info/METADATA
topsis_arihan_102303750-0.0.5.dist-info/WHEEL
topsis_arihan_102303750-0.0.5.dist-info/entry_points.txt
topsis_arihan_102303750-0.0.5.dist-info/top_level.txt
topsis_arihan_102303750-0.0.5.dist-info/RECORD
