Metadata-Version: 2.4
Name: topsis-arihan-102303750
Version: 0.0.5
Summary: TOPSIS implementation as a Python package
Author: Arihan Andotra
Author-email: aandotra_be23@thapar.edu
Requires-Python: >=3.7
Requires-Dist: pandas
Requires-Dist: numpy
Dynamic: author
Dynamic: author-email
Dynamic: description
Dynamic: description-content-type
Dynamic: requires-dist
Dynamic: requires-python
Dynamic: summary
